stefan/__init__.py
stefan/agent/__init__.py
stefan/agent/agent_coder.py
stefan/agent/agent_definition.py
stefan/agent/agent_executor_new.py
stefan/agent/agent_kmp_coder.py
stefan/agent/agent_planner.py
stefan/agent/agent_result.py
stefan/agent/agent_search_code.py
stefan/agent/agent_texts_updater_advanced.py
stefan/agent/agent_texts_updater_simple.py
stefan/agent/agents_factory.py
stefan/agent/agents_formatter.py
stefan/agent/prompt_agents_use_creator.py
stefan/agent/prompt_answer.py
stefan/agent/prompt_file_paths_rules.py
stefan/agent/prompt_metadata_project_context.py
stefan/agent/prompt_template.py
stefan/agent/prompt_tools_use_creator.py
stefan/code_search/.kmpcoder/code_search_tree.json
stefan/code_search/__init__.py
stefan/code_search/code_search_full_text.py
stefan/code_search/code_search_full_text_with_relevancy.py
stefan/code_search/code_search_persistence.py
stefan/code_search/code_search_relevancy.py
stefan/code_search/code_search_tree_creator.py
stefan/code_search/code_search_tree_processor.py
stefan/code_search/file_system_nodes.py
stefan/code_search/llm/__init__.py
stefan/code_search/llm/llm_directory_description.py
stefan/code_search/llm/llm_executor.py
stefan/code_search/llm/llm_file_description.py
stefan/code_search/llm/llm_file_relevancy.py
stefan/code_search/llm/llm_logger.py
stefan/code_search/llm/llm_model.py
stefan/code_search/llm/llm_price_reporter.py
stefan/code_search/llm/llm_tag.py
stefan/data/stefan_result.py
stefan/dependencies/__init__.py
stefan/dependencies/service_locator.py
stefan/execution_context.py
stefan/execution_input_args.py
stefan/execution_tree/execution_tree_builder.py
stefan/execution_tree/execution_tree_data.py
stefan/main.py
stefan/project_configuration.py
stefan/project_metadata.py
stefan/project_metadata_loader.py
stefan/ripgrep/rip_grep_parser.py
stefan/ripgrep/rip_grep_search.py
stefan/scripts/__init__.py
stefan/scripts/script_code_search.py
stefan/scripts/script_sheet_happen.py
stefan-0.1.32.dist-info/METADATA
stefan-0.1.32.dist-info/WHEEL
stefan-0.1.32.dist-info/entry_points.txt
stefan-0.1.32.dist-info/RECORD
